streamlit_wizard/__init__.py
streamlit_wizard/components.py
streamlit_wizard/style.py
streamlit_wizard-0.0.4.dist-info/LICENSE.txt
streamlit_wizard-0.0.4.dist-info/METADATA
streamlit_wizard-0.0.4.dist-info/WHEEL
streamlit_wizard-0.0.4.dist-info/top_level.txt
streamlit_wizard-0.0.4.dist-info/RECORD
