Metadata-Version: 2.1
Name: streamlit-wizard
Version: 0.0.4
Summary: A little streamlit wizard
Author-email: Archy de Berker <archy.deberker@gmail.com>
Project-URL: Homepage, https://github.com/archydeberker/streamlit-wizard
Project-URL: Bug Tracker, https://github.com/archydeberker/streamlit-wizard/issues
Classifier: Programming Language :: Python :: 3
Classifier: License :: OSI Approved :: MIT License
Classifier: Operating System :: OS Independent
Requires-Python: >=3.7
License-File: LICENSE.txt
Requires-Dist: streamlit (>1.11)
